{
  "daily_stats": {
    "2026-01-08": {
      "mouse_clicks": {
        "left": 2484,
        "right": 471,
        "middle": 12
      },
      "keyboard_presses": 14816,
      "mouse_movement_pixels": 4098029.8744423636,
      "sessions": [
        {
          "start": "2026-01-08T12:14:51.387569",
          "end": null
        },
        {
          "start": "2026-01-08T12:30:18.810287",
          "end": null
        }
      ]
    },
    "2026-01-09": {
      "mouse_clicks": {
        "left": 74,
        "right": 9,
        "middle": 1
      },
      "keyboard_presses": 691,
      "mouse_movement_pixels": 109682.83081762481,
      "sessions": [
        {
          "start": "2026-01-09T16:24:53.797496",
          "end": null
        },
        {
          "start": "2026-01-09T16:24:57.470594",
          "end": null
        }
      ]
    }
  },
  "total_clicks": {
    "left": 2557,
    "right": 480,
    "middle": 13
  },
  "total_keys": 15507,
  "total_mouse_movement_pixels": 4207712.705259483,
  "total_sessions": 0
}